nuni_eda-0.4.0.dist-info/METADATA
nuni_eda-0.4.0.dist-info/WHEEL
nuni_eda-0.4.0.dist-info/entry_points.txt
nuni_eda/__init__.py
nuni_eda/cli.py
nuni_eda-0.4.0.dist-info/RECORD
