Metadata-Version: 2.1
Name: nuni-eda
Version: 0.4.0
Summary: Default template for PDM package
Author-Email: nunininu <sgcho0907@gmail.com>
License: MIT
Project-URL: Homepage, https://github.com/nunininu/nuni-eda
Project-URL: Issues, https://github.com/nunininu/nuni-eda/issues
Requires-Python: >=3.10
Requires-Dist: president-speech>=0.9.1
Requires-Dist: pandas>=2.2.3
Requires-Dist: typer>=0.15.1
